yarnlock-1.2.0.dist-info/METADATA
yarnlock-1.2.0.dist-info/WHEEL
yarnlock-1.2.0.dist-info/licenses/LICENSE
yarnlock/__init__.py
yarnlock/py.typed
yarnlock/_lib.pyi
yarnlock/_lib.abi3.so
yarnlock-1.2.0.dist-info/RECORD
