Metadata-Version: 2.4
Name: yarnlock
Version: 1.2.0
Classifier: Development Status :: 5 - Production/Stable
Classifier: Intended Audience :: Developers
Classifier: License :: OSI Approved :: Zero-Clause BSD (0BSD)
Classifier: Operating System :: OS Independent
Classifier: Programming Language :: Python :: 3.10
Classifier: Programming Language :: Python :: 3.11
Classifier: Programming Language :: Python :: 3.12
Classifier: Programming Language :: Python :: 3.13
Classifier: Programming Language :: Python :: 3.9
Classifier: Programming Language :: Python :: Implementation :: CPython
Classifier: Programming Language :: Python :: Implementation :: PyPy
Classifier: Programming Language :: Rust
Classifier: Topic :: Software Development :: Libraries :: Python Modules
Classifier: Typing :: Typed
License-File: LICENSE
Summary: yarn.lock file parser
Keywords: lock,parser,yarn,yarn2dict,yarnlock
Author-email: Kamil Monicz <kamil@monicz.dev>
License: 0BSD
Requires-Python: >=3.9
Project-URL: Issues, https://github.com/Zaczero/yarnlock/issues
Project-URL: Repository, https://github.com/Zaczero/yarnlock
